[{"line":1,"elements":[{"start_timestamp":"2024-04-30T08:06:03.731Z","before":[{"result":{"duration":7820600,"status":"passed"},"match":{"location":"com.MyHooks.HooksAfterAndBefore.setupUrl()"}},{"result":{"duration":2998100,"status":"passed"},"match":{"location":"com.MyHooks.HooksAfterAndBefore.setUp(io.cucumber.java.Scenario)"}}],"line":4,"name":"Search a Product MacBook Air","description":"","id":"amazon-search;search-a-product-macbook-air","after":[{"result":{"duration":4064900,"status":"passed"},"match":{"location":"com.MyHooks.HooksAfterAndBefore.tearDown(io.cucumber.java.Scenario)"}},{"result":{"duration":995800,"status":"passed"},"match":{"location":"com.MyHooks.HooksAfterAndBefore.logout()"}}],"type":"scenario","keyword":"Scenario","steps":[{"result":{"duration":1003200,"status":"passed"},"before":[{"result":{"duration":998200,"status":"passed"},"match":{"location":"com.MyHooks.HooksAfterAndBefore.takescreenshot()"}}],"line":5,"name":"I have a search field on Amazon Page","match":{"location":"com.stepDefinition.HooksDemo.i_have_a_search_field_on_amazon_page()"},"after":[{"result":{"status":"passed"},"match":{"location":"com.MyHooks.HooksAfterAndBefore.refresh()"}}],"keyword":"Given "},{"result":{"duration":8970200,"status":"passed"},"before":[{"result":{"status":"passed"},"match":{"location":"com.MyHooks.HooksAfterAndBefore.takescreenshot()"}}],"line":6,"name":"I search for a product with name \"Apple MacBook Air\" and price 200","match":{"arguments":[{"val":"\"Apple MacBook Air\"","offset":33},{"val":"200","offset":63}],"location":"com.stepDefinition.HooksDemo.i_search_for_a_product_with_name_and_price(java.lang.String,java.lang.Integer)"},"after":[{"result":{"status":"passed"},"match":{"location":"com.MyHooks.HooksAfterAndBefore.refresh()"}}],"keyword":"When "},{"result":{"status":"passed"},"before":[{"result":{"duration":1001900,"status":"passed"},"match":{"location":"com.MyHooks.HooksAfterAndBefore.takescreenshot()"}}],"line":7,"name":"Product with name \"Apple MacBook Air\" should be displayed","match":{"arguments":[{"val":"\"Apple MacBook Air\"","offset":18}],"location":"com.stepDefinition.HooksDemo.product_with_name_should_be_displayed(java.lang.String)"},"after":[{"result":{"status":"passed"},"match":{"location":"com.MyHooks.HooksAfterAndBefore.refresh()"}}],"keyword":"Then "},{"result":{"duration":3988700,"status":"passed"},"before":[{"result":{"status":"passed"},"match":{"location":"com.MyHooks.HooksAfterAndBefore.takescreenshot()"}}],"line":8,"name":"Order id is 12345 and username is \"Naveen\"","match":{"arguments":[{"val":"12345","offset":12},{"val":"\"Naveen\"","offset":34}],"location":"com.stepDefinition.HooksDemo.order_id_is_and_username_is(java.lang.Integer,java.lang.String)"},"after":[{"result":{"status":"passed"},"match":{"location":"com.MyHooks.HooksAfterAndBefore.refresh()"}}],"keyword":"And "}],"tags":[{"name":"@Smoke"}]},{"start_timestamp":"2024-04-30T08:06:03.892Z","before":[{"result":{"status":"passed"},"match":{"location":"com.MyHooks.HooksAfterAndBefore.setupUrl()"}}],"line":10,"name":"Search a Product iPhone","description":"","id":"amazon-search;search-a-product-iphone","after":[{"result":{"status":"passed"},"match":{"location":"com.MyHooks.HooksAfterAndBefore.tearDown(io.cucumber.java.Scenario)"}},{"result":{"status":"passed"},"match":{"location":"com.MyHooks.HooksAfterAndBefore.logout()"}}],"type":"scenario","keyword":"Scenario","steps":[{"result":{"status":"passed"},"before":[{"result":{"status":"passed"},"match":{"location":"com.MyHooks.HooksAfterAndBefore.takescreenshot()"}}],"line":11,"name":"I have a search field on Amazon Page","match":{"location":"com.stepDefinition.HooksDemo.i_have_a_search_field_on_amazon_page()"},"after":[{"result":{"status":"passed"},"match":{"location":"com.MyHooks.HooksAfterAndBefore.refresh()"}}],"keyword":"Given "},{"result":{"duration":1006800,"status":"passed"},"before":[{"result":{"status":"passed"},"match":{"location":"com.MyHooks.HooksAfterAndBefore.takescreenshot()"}}],"line":12,"name":"I search for a product with name \"iPhone\" and price 1200","match":{"arguments":[{"val":"\"iPhone\"","offset":33},{"val":"1200","offset":52}],"location":"com.stepDefinition.HooksDemo.i_search_for_a_product_with_name_and_price(java.lang.String,java.lang.Integer)"},"after":[{"result":{"duration":999600,"status":"passed"},"match":{"location":"com.MyHooks.HooksAfterAndBefore.refresh()"}}],"keyword":"When "},{"result":{"status":"passed"},"before":[{"result":{"duration":5937400,"status":"passed"},"match":{"location":"com.MyHooks.HooksAfterAndBefore.takescreenshot()"}}],"line":13,"name":"Product with name \"iPhone\" should be displayed","match":{"arguments":[{"val":"\"iPhone\"","offset":18}],"location":"com.stepDefinition.HooksDemo.product_with_name_should_be_displayed(java.lang.String)"},"after":[{"result":{"status":"passed"},"match":{"location":"com.MyHooks.HooksAfterAndBefore.refresh()"}}],"keyword":"Then "},{"result":{"status":"passed"},"before":[{"result":{"status":"passed"},"match":{"location":"com.MyHooks.HooksAfterAndBefore.takescreenshot()"}}],"line":14,"name":"Order id is 5677 and username is \"Naveen automation\"","match":{"arguments":[{"val":"5677","offset":12},{"val":"\"Naveen automation\"","offset":33}],"location":"com.stepDefinition.HooksDemo.order_id_is_and_username_is(java.lang.Integer,java.lang.String)"},"after":[{"result":{"status":"passed"},"match":{"location":"com.MyHooks.HooksAfterAndBefore.refresh()"}}],"keyword":"And "}]}],"name":"Amazon Search","description":"","id":"amazon-search","keyword":"Feature","uri":"file:src/main/java/com/features/Hooks.feature","tags":[]}]